[
  {
    "_key": "e93e01f0d291",
    "_type": "block",
    "children": [
      {
        "_key": "fa26b578cfce",
        "_type": "span",
        "marks": [],
        "text": "Heading 1"
      }
    ],
    "markDefs": [],
    "style": "h1"
  },
  {
    "_key": "e93e01f0d291",
    "_type": "block",
    "children": [
      {
        "_key": "fa26b578cfce",
        "_type": "span",
        "marks": ["em", "16219331af82"],
        "text": "Heading"
      },
      {
        "_key": "2b54bee4923d",
        "_type": "span",
        "marks": [],
        "text": " 1"
      }
    ],
    "markDefs": [
      {
        "_type": "link",
        "_key": "16219331af82",
        "href": "kk"
      }
    ],
    "style": "h1"
  },
  {
    "_key": "4988c19856b4",
    "_type": "block",
    "children": [
      {
        "_key": "1f16cc6fa2b1",
        "_type": "span",
        "marks": [],
        "text": "Heading 2"
      }
    ],
    "markDefs": [],
    "style": "h2"
  },
  {
    "_key": "a9870a668555",
    "_type": "block",
    "children": [
      {
        "_key": "88ceab04b8ad",
        "_type": "span",
        "marks": [],
        "text": "heading 3"
      }
    ],
    "markDefs": [],
    "style": "h3"
  },
  {
    "_key": "b24ed7a579bc",
    "_type": "block",
    "children": [
      {
        "_key": "9375707fdc9a",
        "_type": "span",
        "marks": [],
        "text": "Normal"
      }
    ],
    "markDefs": [],
    "style": "normal"
  },
  {
    "_key": "860b7390ec62",
    "_type": "block",
    "children": [
      {
        "_key": "c283c150fcaf",
        "_type": "span",
        "marks": [],
        "text": "Heading 4"
      }
    ],
    "markDefs": [],
    "style": "h4"
  },
  {
    "_key": "fb854c08a662",
    "_type": "block",
    "children": [
      {
        "_key": "f17e3f6d3ab3",
        "_type": "span",
        "marks": [],
        "text": "Heading 5"
      }
    ],
    "markDefs": [],
    "style": "h5"
  },
  {
    "_key": "daed4c7e6913",
    "_type": "block",
    "children": [
      {
        "_key": "9567ffaa7cc1",
        "_type": "span",
        "marks": [],
        "text": "Heading 6"
      }
    ],
    "markDefs": [],
    "style": "h6"
  },
  {
    "_key": "9a7dc720b40f",
    "_type": "block",
    "children": [
      {
        "_key": "81e30af6bfff",
        "_type": "span",
        "marks": [],
        "text": "Quote"
      }
    ],
    "markDefs": [],
    "style": "blockquote"
  },
  {
    "_key": "813f8df0e201",
    "_type": "block",
    "children": [
      {
        "_key": "c01e23189243",
        "_type": "span",
        "marks": ["strong"],
        "text": "Bold"
      }
    ],
    "markDefs": [],
    "style": "normal"
  },
  {
    "_key": "2a8819f6a71c",
    "_type": "block",
    "children": [
      {
        "_key": "4d10c9fee553",
        "_type": "span",
        "marks": ["em"],
        "text": "Italic"
      }
    ],
    "markDefs": [],
    "style": "normal"
  },
  {
    "_key": "62919eab7365",
    "_type": "block",
    "children": [
      {
        "_key": "c662c4005747",
        "_type": "span",
        "marks": ["code"],
        "text": "code"
      }
    ],
    "markDefs": [],
    "style": "normal"
  },
  {
    "_key": "e7183ac9a865",
    "_type": "block",
    "children": [
      {
        "_key": "f42716a0d5b7",
        "_type": "span",
        "marks": ["underline"],
        "text": "Underline"
      }
    ],
    "markDefs": [],
    "style": "normal"
  },
  {
    "_key": "b2591cbd900c",
    "_type": "block",
    "children": [
      {
        "_key": "973191dc1b95",
        "_type": "span",
        "marks": ["strike-through"],
        "text": "Strike"
      }
    ],
    "markDefs": [],
    "style": "normal"
  },
  {
    "_key": "57313d4e80ba",
    "_type": "block",
    "children": [
      {
        "_key": "aaf98a804fd7",
        "_type": "span",
        "marks": [],
        "text": "Bullet 1"
      }
    ],
    "level": 1,
    "listItem": "bullet",
    "markDefs": [],
    "style": "normal"
  },
  {
    "_key": "8e50e8785c01",
    "_type": "block",
    "children": [
      {
        "_key": "966e12dda6bf",
        "_type": "span",
        "marks": [],
        "text": "Bullet 2"
      }
    ],
    "level": 1,
    "listItem": "bullet",
    "markDefs": [],
    "style": "normal"
  },
  {
    "_key": "fad023d77e40",
    "_type": "block",
    "children": [
      {
        "_key": "4a37c6ecddd1",
        "_type": "span",
        "marks": [],
        "text": "Number 1"
      }
    ],
    "level": 1,
    "listItem": "number",
    "markDefs": [],
    "style": "normal"
  },
  {
    "_key": "eac8749a7e3e",
    "_type": "block",
    "children": [
      {
        "_key": "808d17ca6c67",
        "_type": "span",
        "marks": [],
        "text": "Number 2"
      }
    ],
    "level": 1,
    "listItem": "number",
    "markDefs": [],
    "style": "normal"
  },
  {
    "_key": "b6b2037a6435",
    "_type": "block",
    "markDefs": [],
    "style": "normal",
    "children": [
      {
        "_key": "c7bed01c3fb3",
        "_type": "span",
        "marks": [],
        "text": ""
      }
    ]
  },
  {
    "_key": "46b09506dd35",
    "_type": "block",
    "markDefs": [],
    "style": "normal",
    "children": [
      {
        "_key": "f217c2ab8e39",
        "_type": "span",
        "marks": [],
        "text": "Another Number 1"
      }
    ],
    "level": 1,
    "listItem": "number"
  },
  {
    "_key": "34d9c57fbaf3",
    "_type": "block",
    "markDefs": [],
    "style": "normal",
    "level": 1,
    "listItem": "number",
    "children": [
      {
        "_key": "c13242d5e17d",
        "_type": "span",
        "marks": [],
        "text": "Another Number 2"
      }
    ]
  },
  {
    "_key": "1f590fcc1795",
    "_type": "block",
    "children": [
      {
        "_key": "23da37ff32c4",
        "_type": "span",
        "marks": ["e530d5c195bd"],
        "text": "Link"
      }
    ],
    "markDefs": [
      {
        "_key": "e530d5c195bd",
        "_type": "link",
        "href": "www.google.com"
      }
    ],
    "style": "normal"
  },
  {
    "_key": "e651350853df",
    "_type": "block",
    "children": [
      {
        "_key": "de8cc16fd81b",
        "_type": "span",
        "marks": ["strong"],
        "text": "Multiple"
      },
      {
        "_key": "879cce8876a3",
        "_type": "span",
        "marks": [],
        "text": " "
      },
      {
        "_key": "1dea88dc85d5",
        "_type": "span",
        "marks": ["em"],
        "text": "stuff"
      },
      {
        "_key": "290add67a827",
        "_type": "span",
        "marks": [],
        "text": " "
      },
      {
        "_key": "d44fd6cc5b09",
        "_type": "span",
        "marks": ["strong", "em", "underline"],
        "text": "boldAndItalicAndUnderline"
      }
    ],
    "markDefs": [],
    "style": "normal"
  }
]
